harlequin_postgres/__init__.py
harlequin_postgres/adapter.py
harlequin_postgres/catalog.py
harlequin_postgres/cli_options.py
harlequin_postgres/completions.py
harlequin_postgres/interactions.py
harlequin_postgres/keywords.tsv
harlequin_postgres/loaders.py
harlequin_postgres/py.typed
harlequin_postgres-1.2.2.dist-info/LICENSE
harlequin_postgres-1.2.2.dist-info/METADATA
harlequin_postgres-1.2.2.dist-info/WHEEL
harlequin_postgres-1.2.2.dist-info/entry_points.txt
harlequin_postgres-1.2.2.dist-info/RECORD
