Metadata-Version: 2.1
Name: harlequin-postgres
Version: 1.2.2
Summary: A Harlequin adapter for Postgres.
License: MIT
Author: Ted Conbeer
Author-email: tconbeer@users.noreply.github.com
Requires-Python: >=3.9,<3.14
Classifier: License :: OSI Approved :: MIT License
Classifier: Programming Language :: Python :: 3
Classifier: Programming Language :: Python :: 3.9
Classifier: Programming Language :: Python :: 3.10
Classifier: Programming Language :: Python :: 3.11
Requires-Dist: harlequin (>=1.25,<3)
Requires-Dist: psycopg[binary,pool] (>=3.2,<4.0)
